faadelays/__init__.py
faadelays-2023.9.0.dist-info/LICENSE
faadelays-2023.9.0.dist-info/METADATA
faadelays-2023.9.0.dist-info/WHEEL
faadelays-2023.9.0.dist-info/top_level.txt
faadelays-2023.9.0.dist-info/RECORD
