Metadata-Version: 2.1
Name: faadelays
Version: 2023.9.0
Summary: A package to retrieve FAA airport status
Author-email: Nathan Tilley <nathan@tilley.xyz>
License: MIT License
Project-URL: Homepage, https://github.com/ntilley905/faadelays
Project-URL: Bug Tracker, https://github.com/ntilley905/faadelays/issues
Classifier: Programming Language :: Python :: 3
Classifier: License :: OSI Approved :: MIT License
Classifier: Operating System :: OS Independent
Requires-Python: >=3.7
License-File: LICENSE
Requires-Dist: aiohttp
